{
  "generated_at": "2026-07-03T21:09:08.977914+00:00",
  "source": "pinnacle/outright",
  "league": 2686,
  "oddsByEn": {
    "Argentina": 445,
    "Australia": 20000,
    "Belgium": 5000,
    "Brazil": 1200,
    "Canada": 25000,
    "Cape Verde": 100000,
    "Colombia": 3000,
    "Egypt": 20000,
    "England": 1000,
    "France": 190,
    "Ghana": 50000,
    "Mexico": 2800,
    "Morocco": 3300,
    "Norway": 4000,
    "Paraguay": 50000,
    "Portugal": 1200,
    "Spain": 600,
    "Switzerland": 6600,
    "USA": 3300
  },
  "aliveEn": [
    "Argentina",
    "Australia",
    "Belgium",
    "Brazil",
    "Canada",
    "Cape Verde",
    "Colombia",
    "Egypt",
    "England",
    "France",
    "Ghana",
    "Mexico",
    "Morocco",
    "Norway",
    "Paraguay",
    "Portugal",
    "Spain",
    "Switzerland",
    "USA"
  ]
}