{
  "generated_at": "2026-06-22T03:48:08.664370+00:00",
  "model": {
    "devig_method": "shin",
    "rho": -0.06
  },
  "lead_minutes": 5,
  "matches": [
    {
      "scoreline": "1-0",
      "p_scoreline": 0.1309,
      "p_home": 0.648,
      "p_draw": 0.2233,
      "p_away": 0.1286,
      "xg_home": 1.91,
      "xg_away": 0.73,
      "top_scorelines": [
        [
          "1-0",
          0.1309
        ],
        [
          "2-0",
          0.1306
        ],
        [
          "1-1",
          0.1054
        ],
        [
          "2-1",
          0.0949
        ]
      ],
      "residual": 0.005,
      "verdict": "BET",
      "date": "2026-06-22",
      "match_id": 1620858180,
      "home": "Argentina",
      "away": "Austria",
      "kickoff_utc": "2026-06-22T17:00:00+00:00",
      "is_closing": false,
      "captured_at": "2026-06-22T03:48:08.664370+00:00"
    },
    {
      "scoreline": "3-0",
      "p_scoreline": 0.1459,
      "p_home": 0.9099,
      "p_draw": 0.0711,
      "p_away": 0.019,
      "xg_home": 3.36,
      "xg_away": 0.41,
      "top_scorelines": [
        [
          "3-0",
          0.1459
        ],
        [
          "2-0",
          0.1302
        ],
        [
          "4-0",
          0.1227
        ],
        [
          "5-0",
          0.0825
        ]
      ],
      "residual": 0.0104,
      "verdict": "BET",
      "date": "2026-06-22",
      "match_id": 1627256763,
      "home": "France",
      "away": "Iraq",
      "kickoff_utc": "2026-06-22T21:00:00+00:00",
      "is_closing": false,
      "captured_at": "2026-06-22T03:48:08.664370+00:00"
    },
    {
      "scoreline": "1-1",
      "p_scoreline": 0.1288,
      "p_home": 0.4271,
      "p_draw": 0.2705,
      "p_away": 0.3024,
      "xg_home": 1.48,
      "xg_away": 1.21,
      "top_scorelines": [
        [
          "1-1",
          0.1288
        ],
        [
          "1-0",
          0.0931
        ],
        [
          "2-1",
          0.09
        ],
        [
          "0-0",
          0.0751
        ]
      ],
      "residual": 0.0054,
      "verdict": "BET",
      "date": "2026-06-23",
      "match_id": 1620849626,
      "home": "Norway",
      "away": "Senegal",
      "kickoff_utc": "2026-06-23T00:00:00+00:00",
      "is_closing": false,
      "captured_at": "2026-06-22T03:48:08.664370+00:00"
    },
    {
      "scoreline": "0-1",
      "p_scoreline": 0.1229,
      "p_home": 0.1515,
      "p_draw": 0.233,
      "p_away": 0.6155,
      "xg_home": 0.81,
      "xg_away": 1.86,
      "top_scorelines": [
        [
          "0-1",
          0.1229
        ],
        [
          "0-2",
          0.1199
        ],
        [
          "1-1",
          0.1107
        ],
        [
          "1-2",
          0.097
        ]
      ],
      "residual": 0.0055,
      "verdict": "BET",
      "date": "2026-06-23",
      "match_id": 1627256480,
      "home": "Jordan",
      "away": "Algeria",
      "kickoff_utc": "2026-06-23T03:00:00+00:00",
      "is_closing": false,
      "captured_at": "2026-06-22T03:48:08.664370+00:00"
    },
    {
      "scoreline": "2-0",
      "p_scoreline": 0.1511,
      "p_home": 0.8086,
      "p_draw": 0.1395,
      "p_away": 0.0519,
      "xg_home": 2.54,
      "xg_away": 0.52,
      "top_scorelines": [
        [
          "2-0",
          0.1511
        ],
        [
          "3-0",
          0.1282
        ],
        [
          "1-0",
          0.115
        ],
        [
          "4-0",
          0.0815
        ]
      ],
      "residual": 0.0089,
      "verdict": "BET",
      "date": "2026-06-23",
      "match_id": 1620849621,
      "home": "Portugal",
      "away": "Uzbekistan",
      "kickoff_utc": "2026-06-23T17:00:00+00:00",
      "is_closing": false,
      "captured_at": "2026-06-22T03:48:08.664370+00:00"
    },
    {
      "scoreline": "2-0",
      "p_scoreline": 0.1489,
      "p_home": 0.7915,
      "p_draw": 0.1493,
      "p_away": 0.0592,
      "xg_home": 2.47,
      "xg_away": 0.55,
      "top_scorelines": [
        [
          "2-0",
          0.1489
        ],
        [
          "3-0",
          0.1226
        ],
        [
          "1-0",
          0.1166
        ],
        [
          "2-1",
          0.0819
        ]
      ],
      "residual": 0.0058,
      "verdict": "BET",
      "date": "2026-06-23",
      "match_id": 1627257732,
      "home": "England",
      "away": "Ghana",
      "kickoff_utc": "2026-06-23T20:00:00+00:00",
      "is_closing": false,
      "captured_at": "2026-06-22T03:48:08.664370+00:00"
    },
    {
      "scoreline": "0-1",
      "p_scoreline": 0.1234,
      "p_home": 0.1422,
      "p_draw": 0.2272,
      "p_away": 0.6306,
      "xg_home": 0.79,
      "xg_away": 1.9,
      "top_scorelines": [
        [
          "0-1",
          0.1234
        ],
        [
          "0-2",
          0.123
        ],
        [
          "1-1",
          0.1079
        ],
        [
          "1-2",
          0.0967
        ]
      ],
      "residual": 0.0029,
      "verdict": "BET",
      "date": "2026-06-23",
      "match_id": 1620849620,
      "home": "Panama",
      "away": "Croatia",
      "kickoff_utc": "2026-06-23T23:00:00+00:00",
      "is_closing": false,
      "captured_at": "2026-06-22T03:48:08.664370+00:00"
    },
    {
      "scoreline": "1-0",
      "p_scoreline": 0.1585,
      "p_home": 0.6329,
      "p_draw": 0.2424,
      "p_away": 0.1247,
      "xg_home": 1.72,
      "xg_away": 0.63,
      "top_scorelines": [
        [
          "1-0",
          0.1585
        ],
        [
          "2-0",
          0.1417
        ],
        [
          "1-1",
          0.1092
        ],
        [
          "0-0",
          0.1019
        ]
      ],
      "residual": 0.0073,
      "verdict": "BET",
      "date": "2026-06-24",
      "match_id": 1627257733,
      "home": "Colombia",
      "away": "DR Congo",
      "kickoff_utc": "2026-06-24T02:00:00+00:00",
      "is_closing": false,
      "captured_at": "2026-06-22T03:48:08.664370+00:00"
    },
    {
      "scoreline": "2-0",
      "p_scoreline": 0.1155,
      "p_home": 0.6767,
      "p_draw": 0.1979,
      "p_away": 0.1254,
      "xg_home": 2.19,
      "xg_away": 0.84,
      "top_scorelines": [
        [
          "2-0",
          0.1155
        ],
        [
          "1-0",
          0.1
        ],
        [
          "2-1",
          0.0973
        ],
        [
          "1-1",
          0.0941
        ]
      ],
      "residual": 0.0047,
      "verdict": "BET",
      "date": "2026-06-24",
      "match_id": 1627256764,
      "home": "Bosnia and Herzegovina",
      "away": "Qatar",
      "kickoff_utc": "2026-06-24T19:00:00+00:00",
      "is_closing": false,
      "captured_at": "2026-06-22T03:48:08.664370+00:00"
    },
    {
      "scoreline": "1-1",
      "p_scoreline": 0.1364,
      "p_home": 0.403,
      "p_draw": 0.2871,
      "p_away": 0.31,
      "xg_home": 1.32,
      "xg_away": 1.13,
      "top_scorelines": [
        [
          "1-1",
          0.1364
        ],
        [
          "1-0",
          0.1063
        ],
        [
          "0-0",
          0.0939
        ],
        [
          "0-1",
          0.0896
        ]
      ],
      "residual": 0.0157,
      "verdict": "BET",
      "date": "2026-06-24",
      "match_id": 1620858186,
      "home": "Switzerland",
      "away": "Canada",
      "kickoff_utc": "2026-06-24T19:00:00+00:00",
      "is_closing": false,
      "captured_at": "2026-06-22T03:48:08.664370+00:00"
    },
    {
      "scoreline": "2-0",
      "p_scoreline": 0.1479,
      "p_home": 0.824,
      "p_draw": 0.1292,
      "p_away": 0.0469,
      "xg_home": 2.66,
      "xg_away": 0.52,
      "top_scorelines": [
        [
          "2-0",
          0.1479
        ],
        [
          "3-0",
          0.131
        ],
        [
          "1-0",
          0.1079
        ],
        [
          "4-0",
          0.087
        ]
      ],
      "residual": 0.0072,
      "verdict": "BET",
      "date": "2026-06-24",
      "match_id": 1631342070,
      "home": "Morocco",
      "away": "Haiti",
      "kickoff_utc": "2026-06-24T22:00:00+00:00",
      "is_closing": false,
      "captured_at": "2026-06-22T03:48:08.664370+00:00"
    },
    {
      "scoreline": "0-2",
      "p_scoreline": 0.1358,
      "p_home": 0.107,
      "p_draw": 0.2024,
      "p_away": 0.6906,
      "xg_home": 0.69,
      "xg_away": 2.07,
      "top_scorelines": [
        [
          "0-2",
          0.1358
        ],
        [
          "0-1",
          0.1259
        ],
        [
          "1-1",
          0.0958
        ],
        [
          "0-3",
          0.0937
        ]
      ],
      "residual": 0.011,
      "verdict": "BET",
      "date": "2026-06-24",
      "match_id": 1620865469,
      "home": "Scotland",
      "away": "Brazil",
      "kickoff_utc": "2026-06-24T22:00:00+00:00",
      "is_closing": false,
      "captured_at": "2026-06-22T03:48:08.664370+00:00"
    }
  ]
}