{
  "generated_at": "2026-07-19T11:35:56.972903+00:00",
  "model": {
    "devig_method": "shin",
    "rho": -0.06
  },
  "lead_minutes": 5,
  "matches": [
    {
      "scoreline": "1-1",
      "p_scoreline": 0.1372,
      "p_home": 0.4383,
      "p_draw": 0.2928,
      "p_away": 0.2688,
      "xg_home": 1.33,
      "xg_away": 0.98,
      "top_scorelines": [
        [
          "1-1",
          0.1372
        ],
        [
          "1-0",
          0.1238
        ],
        [
          "0-0",
          0.1067
        ],
        [
          "0-1",
          0.0896
        ]
      ],
      "residual": 0.012,
      "verdict": "BET",
      "date": "2026-07-19",
      "match_id": 1632548671,
      "home": "Spain",
      "away": "Argentina",
      "kickoff_utc": "2026-07-19T19:00:00+00:00",
      "is_closing": false,
      "captured_at": "2026-07-19T11:35:56.972903+00:00"
    }
  ]
}