{
  "generated_at": "2026-06-27T12:15:14.711573+00:00",
  "model": {
    "devig_method": "shin",
    "rho": -0.06
  },
  "lead_minutes": 5,
  "matches": [
    {
      "scoreline": "1-0",
      "p_scoreline": 0.1475,
      "p_home": 0.5315,
      "p_draw": 0.2788,
      "p_away": 0.1897,
      "xg_home": 1.48,
      "xg_away": 0.78,
      "top_scorelines": [
        [
          "1-0",
          0.1475
        ],
        [
          "1-1",
          0.1276
        ],
        [
          "2-0",
          0.1145
        ],
        [
          "0-0",
          0.1118
        ]
      ],
      "residual": 0.0141,
      "verdict": "BET",
      "date": "2026-06-27",
      "match_id": 1631338308,
      "home": "Croatia",
      "away": "Ghana",
      "kickoff_utc": "2026-06-27T21:00:00+00:00",
      "is_closing": false,
      "captured_at": "2026-06-27T12:15:14.711573+00:00"
    },
    {
      "scoreline": "0-2",
      "p_scoreline": 0.1297,
      "p_home": 0.0492,
      "p_draw": 0.1212,
      "p_away": 0.8295,
      "xg_home": 0.6,
      "xg_away": 2.84,
      "top_scorelines": [
        [
          "0-2",
          0.1297
        ],
        [
          "0-3",
          0.1228
        ],
        [
          "0-1",
          0.0881
        ],
        [
          "0-4",
          0.0872
        ]
      ],
      "residual": 0.0071,
      "verdict": "BET",
      "date": "2026-06-27",
      "match_id": 1631338307,
      "home": "Panama",
      "away": "England",
      "kickoff_utc": "2026-06-27T21:00:00+00:00",
      "is_closing": false,
      "captured_at": "2026-06-27T12:15:14.711573+00:00"
    },
    {
      "scoreline": "1-1",
      "p_scoreline": 0.122,
      "p_home": 0.2594,
      "p_draw": 0.2574,
      "p_away": 0.4833,
      "xg_home": 1.15,
      "xg_away": 1.65,
      "top_scorelines": [
        [
          "1-1",
          0.122
        ],
        [
          "1-2",
          0.0952
        ],
        [
          "0-1",
          0.0928
        ],
        [
          "0-2",
          0.0825
        ]
      ],
      "residual": 0.0055,
      "verdict": "BET",
      "date": "2026-06-27",
      "match_id": 1631338311,
      "home": "Colombia",
      "away": "Portugal",
      "kickoff_utc": "2026-06-27T23:30:00+00:00",
      "is_closing": false,
      "captured_at": "2026-06-27T12:15:14.711573+00:00"
    },
    {
      "scoreline": "1-0",
      "p_scoreline": 0.1394,
      "p_home": 0.5897,
      "p_draw": 0.2516,
      "p_away": 0.1588,
      "xg_home": 1.69,
      "xg_away": 0.76,
      "top_scorelines": [
        [
          "1-0",
          0.1394
        ],
        [
          "2-0",
          0.1234
        ],
        [
          "1-1",
          0.1175
        ],
        [
          "2-1",
          0.0936
        ]
      ],
      "residual": 0.0089,
      "verdict": "BET",
      "date": "2026-06-27",
      "match_id": 1631342072,
      "home": "DR Congo",
      "away": "Uzbekistan",
      "kickoff_utc": "2026-06-27T23:30:00+00:00",
      "is_closing": false,
      "captured_at": "2026-06-27T12:15:14.711573+00:00"
    },
    {
      "scoreline": "0-0",
      "p_scoreline": 0.1774,
      "p_home": 0.2849,
      "p_draw": 0.3462,
      "p_away": 0.369,
      "xg_home": 0.81,
      "xg_away": 0.96,
      "top_scorelines": [
        [
          "0-0",
          0.1774
        ],
        [
          "0-1",
          0.1554
        ],
        [
          "1-1",
          0.1404
        ],
        [
          "1-0",
          0.1295
        ]
      ],
      "residual": 0.0535,
      "verdict": "SKIP",
      "date": "2026-06-28",
      "match_id": 1631350199,
      "home": "Algeria",
      "away": "Austria",
      "kickoff_utc": "2026-06-28T02:00:00+00:00",
      "is_closing": false,
      "captured_at": "2026-06-27T12:15:14.711573+00:00"
    },
    {
      "scoreline": "0-2",
      "p_scoreline": 0.1448,
      "p_home": 0.0408,
      "p_draw": 0.1173,
      "p_away": 0.8419,
      "xg_home": 0.5,
      "xg_away": 2.79,
      "top_scorelines": [
        [
          "0-2",
          0.1448
        ],
        [
          "0-3",
          0.1344
        ],
        [
          "0-1",
          0.1008
        ],
        [
          "0-4",
          0.0936
        ]
      ],
      "residual": 0.0075,
      "verdict": "BET",
      "date": "2026-06-28",
      "match_id": 1631342069,
      "home": "Jordan",
      "away": "Argentina",
      "kickoff_utc": "2026-06-28T02:00:00+00:00",
      "is_closing": false,
      "captured_at": "2026-06-27T12:15:14.711573+00:00"
    },
    {
      "scoreline": "0-1",
      "p_scoreline": 0.1445,
      "p_home": 0.1798,
      "p_draw": 0.2697,
      "p_away": 0.5505,
      "xg_home": 0.78,
      "xg_away": 1.55,
      "top_scorelines": [
        [
          "0-1",
          0.1445
        ],
        [
          "1-1",
          0.1245
        ],
        [
          "0-2",
          0.1174
        ],
        [
          "0-0",
          0.1048
        ]
      ],
      "residual": 0.0051,
      "verdict": "BET",
      "date": "2026-06-28",
      "match_id": 1632123645,
      "home": "South Africa",
      "away": "Canada",
      "kickoff_utc": "2026-06-28T19:00:00+00:00",
      "is_closing": false,
      "captured_at": "2026-06-27T12:15:14.711573+00:00"
    },
    {
      "scoreline": "1-0",
      "p_scoreline": 0.1281,
      "p_home": 0.5663,
      "p_draw": 0.2544,
      "p_away": 0.1793,
      "xg_home": 1.68,
      "xg_away": 0.84,
      "top_scorelines": [
        [
          "1-0",
          0.1281
        ],
        [
          "1-1",
          0.1203
        ],
        [
          "2-0",
          0.1134
        ],
        [
          "2-1",
          0.0954
        ]
      ],
      "residual": 0.0057,
      "verdict": "BET",
      "date": "2026-06-29",
      "match_id": 1632130818,
      "home": "Brazil",
      "away": "Japan",
      "kickoff_utc": "2026-06-29T17:00:00+00:00",
      "is_closing": false,
      "captured_at": "2026-06-27T12:15:14.711573+00:00"
    },
    {
      "scoreline": "2-0",
      "p_scoreline": 0.1326,
      "p_home": 0.7019,
      "p_draw": 0.1942,
      "p_away": 0.1039,
      "xg_home": 2.15,
      "xg_away": 0.71,
      "top_scorelines": [
        [
          "2-0",
          0.1326
        ],
        [
          "1-0",
          0.1179
        ],
        [
          "3-0",
          0.0952
        ],
        [
          "2-1",
          0.0939
        ]
      ],
      "residual": 0.006,
      "verdict": "BET",
      "date": "2026-06-29",
      "match_id": 1632164494,
      "home": "Germany",
      "away": "Paraguay",
      "kickoff_utc": "2026-06-29T20:30:00+00:00",
      "is_closing": false,
      "captured_at": "2026-06-27T12:15:14.711573+00:00"
    }
  ]
}