{
  "generated_at": "2026-07-17T20:25:33.536161+00:00",
  "model": {
    "devig_method": "shin",
    "rho": -0.06
  },
  "lead_minutes": 5,
  "matches": [
    {
      "scoreline": "1-1",
      "p_scoreline": 0.0974,
      "p_home": 0.5176,
      "p_draw": 0.2253,
      "p_away": 0.2571,
      "xg_home": 2.04,
      "xg_away": 1.4,
      "top_scorelines": [
        [
          "1-1",
          0.0974
        ],
        [
          "2-1",
          0.0935
        ],
        [
          "2-0",
          0.0669
        ],
        [
          "2-2",
          0.0653
        ]
      ],
      "residual": 0.0103,
      "verdict": "BET",
      "date": "2026-07-18",
      "match_id": 1632548666,
      "home": "France",
      "away": "England",
      "kickoff_utc": "2026-07-18T21:00:00+00:00",
      "is_closing": false,
      "captured_at": "2026-07-17T20:25:33.536161+00:00"
    },
    {
      "scoreline": "1-1",
      "p_scoreline": 0.1374,
      "p_home": 0.4305,
      "p_draw": 0.2923,
      "p_away": 0.2772,
      "xg_home": 1.32,
      "xg_away": 1.01,
      "top_scorelines": [
        [
          "1-1",
          0.1374
        ],
        [
          "1-0",
          0.1204
        ],
        [
          "0-0",
          0.1046
        ],
        [
          "0-1",
          0.0901
        ]
      ],
      "residual": 0.0137,
      "verdict": "BET",
      "date": "2026-07-19",
      "match_id": 1632548671,
      "home": "Spain",
      "away": "Argentina",
      "kickoff_utc": "2026-07-19T19:00:00+00:00",
      "is_closing": false,
      "captured_at": "2026-07-17T20:25:33.536161+00:00"
    }
  ]
}