{
  "generated_at": "2026-06-27T22:30:17.298956+00:00",
  "model": {
    "devig_method": "shin",
    "rho": -0.06
  },
  "lead_minutes": 5,
  "matches": [
    {
      "scoreline": "1-1",
      "p_scoreline": 0.1163,
      "p_home": 0.2514,
      "p_draw": 0.2479,
      "p_away": 0.5007,
      "xg_home": 1.19,
      "xg_away": 1.76,
      "top_scorelines": [
        [
          "1-1",
          0.1163
        ],
        [
          "1-2",
          0.0965
        ],
        [
          "0-1",
          0.0857
        ],
        [
          "0-2",
          0.0812
        ]
      ],
      "residual": 0.0063,
      "verdict": "BET",
      "date": "2026-06-27",
      "match_id": 1631338311,
      "home": "Colombia",
      "away": "Portugal",
      "kickoff_utc": "2026-06-27T23:30:00+00:00",
      "is_closing": false,
      "captured_at": "2026-06-27T22:30:17.298956+00:00"
    },
    {
      "scoreline": "1-0",
      "p_scoreline": 0.1463,
      "p_home": 0.5645,
      "p_draw": 0.2653,
      "p_away": 0.1702,
      "xg_home": 1.58,
      "xg_away": 0.75,
      "top_scorelines": [
        [
          "1-0",
          0.1463
        ],
        [
          "1-1",
          0.1223
        ],
        [
          "2-0",
          0.1212
        ],
        [
          "0-0",
          0.1039
        ]
      ],
      "residual": 0.0084,
      "verdict": "BET",
      "date": "2026-06-27",
      "match_id": 1631342072,
      "home": "DR Congo",
      "away": "Uzbekistan",
      "kickoff_utc": "2026-06-27T23:30:00+00:00",
      "is_closing": false,
      "captured_at": "2026-06-27T22:30:17.298956+00:00"
    },
    {
      "scoreline": "0-0",
      "p_scoreline": 0.1841,
      "p_home": 0.3374,
      "p_draw": 0.3519,
      "p_away": 0.3106,
      "xg_home": 0.89,
      "xg_away": 0.84,
      "top_scorelines": [
        [
          "0-0",
          0.1841
        ],
        [
          "1-0",
          0.1492
        ],
        [
          "0-1",
          0.1407
        ],
        [
          "1-1",
          0.1406
        ]
      ],
      "residual": 0.0529,
      "verdict": "SKIP",
      "date": "2026-06-28",
      "match_id": 1631350199,
      "home": "Algeria",
      "away": "Austria",
      "kickoff_utc": "2026-06-28T02:00:00+00:00",
      "is_closing": false,
      "captured_at": "2026-06-27T22:30:17.298956+00:00"
    },
    {
      "scoreline": "0-2",
      "p_scoreline": 0.1511,
      "p_home": 0.035,
      "p_draw": 0.1109,
      "p_away": 0.8541,
      "xg_home": 0.45,
      "xg_away": 2.81,
      "top_scorelines": [
        [
          "0-2",
          0.1511
        ],
        [
          "0-3",
          0.1414
        ],
        [
          "0-1",
          0.1047
        ],
        [
          "0-4",
          0.0993
        ]
      ],
      "residual": 0.0109,
      "verdict": "BET",
      "date": "2026-06-28",
      "match_id": 1631342069,
      "home": "Jordan",
      "away": "Argentina",
      "kickoff_utc": "2026-06-28T02:00:00+00:00",
      "is_closing": false,
      "captured_at": "2026-06-27T22:30:17.298956+00:00"
    },
    {
      "scoreline": "0-1",
      "p_scoreline": 0.1458,
      "p_home": 0.167,
      "p_draw": 0.2627,
      "p_away": 0.5702,
      "xg_home": 0.75,
      "xg_away": 1.6,
      "top_scorelines": [
        [
          "0-1",
          0.1458
        ],
        [
          "0-2",
          0.1221
        ],
        [
          "1-1",
          0.1213
        ],
        [
          "0-0",
          0.1022
        ]
      ],
      "residual": 0.0058,
      "verdict": "BET",
      "date": "2026-06-28",
      "match_id": 1632123645,
      "home": "South Africa",
      "away": "Canada",
      "kickoff_utc": "2026-06-28T19:00:00+00:00",
      "is_closing": false,
      "captured_at": "2026-06-27T22:30:17.298956+00:00"
    },
    {
      "scoreline": "1-0",
      "p_scoreline": 0.1279,
      "p_home": 0.568,
      "p_draw": 0.2537,
      "p_away": 0.1783,
      "xg_home": 1.69,
      "xg_away": 0.84,
      "top_scorelines": [
        [
          "1-0",
          0.1279
        ],
        [
          "1-1",
          0.12
        ],
        [
          "2-0",
          0.1137
        ],
        [
          "2-1",
          0.0955
        ]
      ],
      "residual": 0.0057,
      "verdict": "BET",
      "date": "2026-06-29",
      "match_id": 1632130818,
      "home": "Brazil",
      "away": "Japan",
      "kickoff_utc": "2026-06-29T17:00:00+00:00",
      "is_closing": false,
      "captured_at": "2026-06-27T22:30:17.298956+00:00"
    },
    {
      "scoreline": "2-0",
      "p_scoreline": 0.1317,
      "p_home": 0.7048,
      "p_draw": 0.1921,
      "p_away": 0.1032,
      "xg_home": 2.18,
      "xg_away": 0.71,
      "top_scorelines": [
        [
          "2-0",
          0.1317
        ],
        [
          "1-0",
          0.1158
        ],
        [
          "3-0",
          0.0955
        ],
        [
          "2-1",
          0.0939
        ]
      ],
      "residual": 0.006,
      "verdict": "BET",
      "date": "2026-06-29",
      "match_id": 1632164494,
      "home": "Germany",
      "away": "Paraguay",
      "kickoff_utc": "2026-06-29T20:30:00+00:00",
      "is_closing": false,
      "captured_at": "2026-06-27T22:30:17.298956+00:00"
    }
  ]
}